gradsflow/__init__.py
gradsflow/autotasks/__init__.py
gradsflow/autotasks/autosummarization.py
gradsflow/autotasks/autotasks.py
gradsflow/autotasks/autoclassification/__init__.py
gradsflow/autotasks/autoclassification/image.py
gradsflow/autotasks/autoclassification/text/__init__.py
gradsflow/autotasks/autoclassification/text/text.py
gradsflow/autotasks/engine/__init__.py
gradsflow/autotasks/engine/autoclassifier.py
gradsflow/autotasks/engine/automodel.py
gradsflow/autotasks/engine/backend.py
gradsflow/callbacks/__init__.py
gradsflow/callbacks/base.py
gradsflow/callbacks/comet.py
gradsflow/callbacks/gpu.py
gradsflow/callbacks/logger.py
gradsflow/callbacks/progress.py
gradsflow/callbacks/raytune.py
gradsflow/callbacks/runner.py
gradsflow/callbacks/tensorboard.py
gradsflow/callbacks/training.py
gradsflow/callbacks/wandb.py
gradsflow/core/__init__.py
gradsflow/core/base.py
gradsflow/core/metrics.py
gradsflow/data/__init__.py
gradsflow/data/autodata.py
gradsflow/data/base.py
gradsflow/data/common.py
gradsflow/data/image.py
gradsflow/data/mixins.py
gradsflow/data/ray_dataset.py
gradsflow/models/__init__.py
gradsflow/models/base.py
gradsflow/models/constants.py
gradsflow/models/exceptions.py
gradsflow/models/model.py
gradsflow/models/tracker.py
gradsflow/models/utils.py
gradsflow/tuner/__init__.py
gradsflow/tuner/automodel.py
gradsflow/tuner/tuner.py
gradsflow/utility/__init__.py
gradsflow/utility/common.py
gradsflow/utility/data.py
gradsflow/utility/imports.py
gradsflow-0.0.8.post1.dist-info/LICENSE
gradsflow-0.0.8.post1.dist-info/METADATA
gradsflow-0.0.8.post1.dist-info/WHEEL
gradsflow-0.0.8.post1.dist-info/top_level.txt
gradsflow-0.0.8.post1.dist-info/RECORD
