Metadata-Version: 2.1
Name: gradsflow
Version: 0.0.8.post1
Summary: An open-source AutoML Library based on PyTorch
Home-page: https://github.com/gradsflow/gradsflow
Author: Aniket Maurya
Author-email: aniket@gradsflow.com
Project-URL: Bug Tracker, https://github.com/gradsflow/gradsflow/issues
Project-URL: Documentation, https://docs.gradsflow.com
Project-URL: Source Code, https://github.com/gradsflow/gradsflow
Keywords: AutoML,Pytorch,Deep Learning
Classifier: Development Status :: 4 - Beta
Classifier: Intended Audience :: Developers
Classifier: Programming Language :: Python :: 3
Classifier: License :: OSI Approved :: Apache Software License
Classifier: Operating System :: OS Independent
Requires-Python: >=3.7
License-File: LICENSE
Requires-Dist: torch (>=1.4)
Requires-Dist: torchvision
Requires-Dist: ray[default,tune] (>=1.8.0)
Requires-Dist: timm
Requires-Dist: accelerate (>=0.5.0)
Requires-Dist: smart-open (<=5.2.1,>=5.1)
Requires-Dist: rich
Requires-Dist: loguru (>=0.5)
Requires-Dist: torchmetrics (>=0.5.0)
Provides-Extra: dev
Requires-Dist: lightning-flash[image,text] (>=0.5.1) ; extra == 'dev'
Requires-Dist: codecarbon (>=1.2.0) ; extra == 'dev'
Requires-Dist: comet-ml ; extra == 'dev'
Requires-Dist: wandb ; extra == 'dev'
Provides-Extra: test
Requires-Dist: pytest ; extra == 'test'
Requires-Dist: coverage ; extra == 'test'
Requires-Dist: pytest-sugar ; extra == 'test'
